ks_eastmoney_fundamental_api/./.git
ks_eastmoney_fundamental_api/./.gitignore
ks_eastmoney_fundamental_api/./EmQuantAPI.py
ks_eastmoney_fundamental_api/./LICENSE.txt
ks_eastmoney_fundamental_api/./README.en.md
ks_eastmoney_fundamental_api/./README.md
ks_eastmoney_fundamental_api/./__about__.py
ks_eastmoney_fundamental_api/./__init__.py
ks_eastmoney_fundamental_api/./installEmQuantAPI.py
ks_eastmoney_fundamental_api/./ks_eastmoney_fundamental_api.py
ks_eastmoney_fundamental_api/./pyproject.toml
ks_eastmoney_fundamental_api/./requirements.txt
ks_eastmoney_fundamental_api/./setup.py
ks_eastmoney_fundamental_api/./libs/windows/ActivatorLog.txt
ks_eastmoney_fundamental_api/./libs/windows/EmQuantAPI.dll
ks_eastmoney_fundamental_api/./libs/windows/EmQuantAPI_x64.dll
ks_eastmoney_fundamental_api/./libs/windows/LoginActivator.exe
ks_eastmoney_fundamental_api/./libs/windows/ServerList.json.e
ks_eastmoney_fundamental_api/./libs/windows/ServerSelect.txt
ks_eastmoney_fundamental_api/./libs/windows/config.e
ks_eastmoney_fundamental_api/./libs/windows/precentflag.dat
ks_eastmoney_fundamental_api/./libs/windows/userInfo
ks_eastmoney_fundamental_api/./tests/config.py
ks_eastmoney_fundamental_api/./tests/conftest.py
ks_eastmoney_fundamental_api/./tests/test_css_mrq.py
ks_eastmoney_fundamental_api/./tests/test_css_mry.py
ks_eastmoney_fundamental_api/./tests/test_wsd.py
ks_eastmoney_fundamental_api/./testsbak/__init__.py
ks_eastmoney_fundamental_api/./testsbak/config.py
ks_eastmoney_fundamental_api/./testsbak/conftest.py
ks_eastmoney_fundamental_api/./testsbak/fundamental_config.py
ks_eastmoney_fundamental_api/./testsbak/test_ctr.py
ks_eastmoney_fundamental_api-0.0.49.dist-info/METADATA
ks_eastmoney_fundamental_api-0.0.49.dist-info/WHEEL
ks_eastmoney_fundamental_api-0.0.49.dist-info/licenses/LICENSE.txt
ks_eastmoney_fundamental_api-0.0.49.dist-info/RECORD
